{
    "timestamp": "2026-02-28 11:33:46",
    "forecasts": [
        {
            "raw_text": "N winds 10 to 15 kt, increasing to 15 to 20 kt early this afternoon, then diminishing to 10 to 15 kt late. Seas 3 to 5 ft. Wave detail: NE 5 ft at 7 seconds and E 3 ft at 11 seconds. Areas of fog early this morning. Patchy fog late this morning. Patchy drizzle this morning, then patchy very light drizzle early this afternoon. Vsby 1 nm or less this morning.",
            "wind_direction": "N",
            "wind_speed": "10 to 15 kt",
            "wind_commentary": "increasing to 15 to 20 kt early this afternoon",
            "wave_height": "3 to 5 ft",
            "wave_detail_string": "NE 5 ft at 7 seconds and E 3 ft at 11 seconds",
            "swell_components": [
                {
                    "direction": "NE",
                    "height": "5 ft",
                    "period": "7 seconds"
                },
                {
                    "direction": "E",
                    "height": "3 ft",
                    "period": "11 seconds"
                }
            ],
            "primary_swell_direction": "NE",
            "primary_wave_height": "5 ft",
            "primary_wave_period": "7 seconds",
            "period": "Today 2/28"
        },
        {
            "raw_text": "N winds 10 to 15 kt, diminishing to 5 to 10 kt after midnight. Seas 3 to 5 ft. Wave detail: NE 5 ft at 7 seconds and SE 2 ft at 10 seconds. Patchy fog.",
            "wind_direction": "N",
            "wind_speed": "10 to 15 kt",
            "wind_commentary": "diminishing to 5 to 10 kt after midnight",
            "wave_height": "3 to 5 ft",
            "wave_detail_string": "NE 5 ft at 7 seconds and SE 2 ft at 10 seconds",
            "swell_components": [
                {
                    "direction": "NE",
                    "height": "5 ft",
                    "period": "7 seconds"
                },
                {
                    "direction": "SE",
                    "height": "2 ft",
                    "period": "10 seconds"
                }
            ],
            "primary_swell_direction": "NE",
            "primary_wave_height": "5 ft",
            "primary_wave_period": "7 seconds",
            "period": "Tonight 2/28"
        },
        {
            "raw_text": "NW winds 5 to 10 kt, becoming SW in the afternoon. Seas 3 to 4 ft. Wave detail: NE 3 ft at 7 seconds and SE 2 ft at 9 seconds. Patchy fog in the morning.",
            "wind_direction": "NW",
            "wind_speed": "5 to 10 kt",
            "wind_commentary": "becoming SW in the afternoon",
            "wave_height": "3 to 4 ft",
            "wave_detail_string": "NE 3 ft at 7 seconds and SE 2 ft at 9 seconds",
            "swell_components": [
                {
                    "direction": "NE",
                    "height": "3 ft",
                    "period": "7 seconds"
                },
                {
                    "direction": "SE",
                    "height": "2 ft",
                    "period": "9 seconds"
                }
            ],
            "primary_swell_direction": "NE",
            "primary_wave_height": "3 ft",
            "primary_wave_period": "7 seconds",
            "period": "Sun 3/1"
        },
        {
            "raw_text": "N winds 15 to 20 kt, increasing to 20 to 25 kt with gusts up to 30 kt after midnight. Seas 4 to 6 ft, building to 5 to 8 ft after midnight. Wave detail: NE 3 ft at 7 seconds and SW 2 ft at 4 seconds, becoming NE 6 ft at 7 seconds and SE 2 ft at 10 seconds.",
            "wind_direction": "N",
            "wind_speed": "15 to 20 kt",
            "wind_commentary": "increasing to 20 to 25 kt with gusts up to 30 kt after midnight",
            "wind_gusts": "30 kt",
            "wave_height": "4 to 6 ft",
            "wave_commentary": "building to 5 to 8 ft",
            "wave_detail_string": "NE 3 ft at 7 seconds and SW 2 ft at 4 seconds, becoming NE 6 ft at 7 seconds and SE 2 ft at 10 seconds",
            "swell_components": [
                {
                    "direction": "NE",
                    "height": "3 ft",
                    "period": "7 seconds"
                },
                {
                    "direction": "SW",
                    "height": "2 ft",
                    "period": "4 seconds"
                },
                {
                    "direction": "NE",
                    "height": "6 ft",
                    "period": "7 seconds"
                },
                {
                    "direction": "SE",
                    "height": "2 ft",
                    "period": "10 seconds"
                }
            ],
            "primary_swell_direction": "NE",
            "primary_wave_height": "3 ft",
            "primary_wave_period": "7 seconds",
            "period": "Sun Night 3/1"
        },
        {
            "raw_text": "NE winds 20 to 25 kt with gusts up to 30 kt. Seas 6 to 8 ft. Wave detail: NE 7 ft at 8 seconds and SE 2 ft at 10 seconds.",
            "wind_direction": "NE",
            "wind_speed": "20 to 25 kt",
            "wind_gusts": "30 kt",
            "wave_height": "6 to 8 ft",
            "wave_detail_string": "NE 7 ft at 8 seconds and SE 2 ft at 10 seconds",
            "swell_components": [
                {
                    "direction": "NE",
                    "height": "7 ft",
                    "period": "8 seconds"
                },
                {
                    "direction": "SE",
                    "height": "2 ft",
                    "period": "10 seconds"
                }
            ],
            "primary_swell_direction": "NE",
            "primary_wave_height": "7 ft",
            "primary_wave_period": "8 seconds",
            "period": "Mon 3/2"
        },
        {
            "raw_text": "NE winds 15 to 20 kt with gusts up to 25 kt, diminishing to 10 to 15 kt after midnight. Seas 5 to 8 ft. Wave detail: NE 7 ft at 8 seconds and E 5 ft at 10 seconds. A chance of rain after midnight.",
            "wind_direction": "NE",
            "wind_speed": "15 to 20 kt",
            "wind_commentary": "diminishing to 10 to 15 kt after midnight",
            "wind_gusts": "25 kt",
            "wave_height": "5 to 8 ft",
            "wave_detail_string": "NE 7 ft at 8 seconds and E 5 ft at 10 seconds",
            "swell_components": [
                {
                    "direction": "NE",
                    "height": "7 ft",
                    "period": "8 seconds"
                },
                {
                    "direction": "E",
                    "height": "5 ft",
                    "period": "10 seconds"
                }
            ],
            "primary_swell_direction": "NE",
            "primary_wave_height": "7 ft",
            "primary_wave_period": "8 seconds",
            "period": "Mon Night 3/2"
        },
        {
            "raw_text": "E winds 10 to 15 kt, becoming SE in the afternoon. Seas 5 to 7 ft.",
            "wind_direction": "E",
            "wind_speed": "10 to 15 kt",
            "wind_commentary": "becoming SE in the afternoon",
            "wave_height": "5 to 7 ft",
            "period": "Tue 3/3"
        },
        {
            "raw_text": "S winds 10 to 15 kt. Seas 4 to 6 ft.",
            "wind_direction": "S",
            "wind_speed": "10 to 15 kt",
            "wave_height": "4 to 6 ft",
            "period": "Tue Night 3/3"
        },
        {
            "raw_text": "SW winds 5 to 10 kt. Seas 4 to 5 ft.",
            "wind_direction": "SW",
            "wind_speed": "5 to 10 kt",
            "wave_height": "4 to 5 ft",
            "period": "Wed 3/4"
        },
        {
            "raw_text": "S winds around 10 kt. Seas 4 to 5 ft.",
            "wind_direction": "S",
            "wind_speed": "10 kt",
            "wave_height": "4 to 5 ft",
            "period": "Wed Night 3/4"
        }
    ]
}